LICENSE
MANIFEST.in
README
setup.py
src/sleipnir/__init__.py
src/sleipnir.components.egg-info/PKG-INFO
src/sleipnir.components.egg-info/SOURCES.txt
src/sleipnir.components.egg-info/dependency_links.txt
src/sleipnir.components.egg-info/namespace_packages.txt
src/sleipnir.components.egg-info/not-zip-safe
src/sleipnir.components.egg-info/requires.txt
src/sleipnir.components.egg-info/top_level.txt
src/sleipnir/components/__init__.py
src/sleipnir/components/_log.py
src/sleipnir/components/components.py
src/sleipnir/components/constants.py
src/sleipnir/components/entrypoint.py
src/sleipnir/components/exceptions.py
src/sleipnir/components/loaders.py
src/sleipnir/components/manager.py
src/sleipnir/components/metaclass.py
src/sleipnir/components/interfaces/__init__.py
src/sleipnir/components/interfaces/loader.py
src/sleipnir/components/tests/__init__.py
src/sleipnir/components/tests/test_core.py
src/sleipnir/components/tests/test_loader.py