Metadata-Version: 1.0
Name: sleipnir.components
Version: 0.2rc1
Summary: A Component subsystem for Sleipnir Project
Home-page: http://sleipnir.liberalia.net/
Author: Carlos Martín
Author-email: cmartin@liberalia.net
License: Trac BSD License
Platform: UNKNOWN
Classifier: Development Status :: 4 - Beta
Classifier: License :: OSI Approved :: BSD License
Classifier: Operating System :: OS Independent
Classifier: Programming Language :: Python :: 2.6
Classifier: Programming Language :: Python :: 2.7
Classifier: Topic :: Software Development
